{
    "id": "resilience",
    "name": "Resilience",
    "description": "Your ability to endure damage and keep fighting.",
    "type": "combat",
    "milestones": [
        {
            "level": 1,
            "bonuses": [
                {
                    "type": "attribute",
                    "id": "constitution",
                    "value": 1
                }
            ]
        },
        {
            "level": 2,
            "bonuses": [
                {
                    "type": "combat",
                    "id": "defense",
                    "value": 1
                }
            ]
        },
        {
            "level": 3,
            "bonuses": [
                {
                    "type": "attribute",
                    "id": "constitution",
                    "value": 1
                }
            ]
        },
        {
            "level": 4,
            "bonuses": [
                {
                    "type": "combat",
                    "id": "defense",
                    "value": 1
                }
            ]
        },
        {
            "level": 5,
            "bonuses": [
                {
                    "type": "attribute",
                    "id": "constitution",
                    "value": 1
                },
                {
                    "type": "combat",
                    "id": "defense",
                    "value": 1
                }
            ]
        },
        {
            "level": 6,
            "bonuses": [
                {
                    "type": "combat",
                    "id": "defense",
                    "value": 1
                }
            ]
        }
    ]
}